tests/__init__.py
tests/conftest.py
tests/test_dbinspector.py
dbinspector-0.1.1.dist-info/LICENSE
dbinspector-0.1.1.dist-info/METADATA
dbinspector-0.1.1.dist-info/WHEEL
dbinspector-0.1.1.dist-info/top_level.txt
dbinspector-0.1.1.dist-info/RECORD
