Metadata-Version: 2.1
Name: dbinspector
Version: 0.1.1
Summary: A libray for use with SQLAlchemy to count queires, log queries, etc...
Home-page: https://github.com/cgons/dbinspector
Author: Chrys Gonsalves
Author-email: cgons@pcxchange.ca
License: UNKNOWN
Platform: UNKNOWN
Classifier: Programming Language :: Python :: 3
Classifier: License :: OSI Approved :: MIT License
Classifier: Operating System :: OS Independent
Requires-Dist: psycopg2-binary
Requires-Dist: sqlalchemy
Provides-Extra: dev
Requires-Dist: black ; extra == 'dev'
Requires-Dist: ipdb ; extra == 'dev'
Requires-Dist: ipython ; extra == 'dev'
Requires-Dist: pytest ; extra == 'dev'
Requires-Dist: wheel ; extra == 'dev'
